StatusDisplay/status_display.v
module status_display#(
    parameter pIDLE = 3'b000,
    parameter pWAIT_COIN = 3'b001,
    parameter pSELECT_PRODUCT = 3'b010,
    parameter pDISPENSE_CHANGE = 3'b011,
    parameter pRETURN_MONEY = 3'b100
)(
    input wire clk,
    input wire rst_n,
    input wire cancel,
    input wire display_status_en,
    input wire product_dispense_done,
    input wire change_dispense_done,
    input wire [2:0] state_out,
    output reg [7:0] status_display,
    output reg [3:0] led_indicators
);
    

    always @(posedge clk or negedge rst_n) begin
    if (!rst_n || cancel) begin
        status_display   <= 8'b0000_0000;
        led_indicators   <= 4'b0000;
    end else if (display_status_en) begin
        case (state_out)
            pIDLE: begin
                status_display <= 8'h49;      // Hiển thị "I" = 0x49
                led_indicators <= 4'b0001;    // LED trạng thái IDLE
            end
            pWAIT_COIN: begin
                status_display <= 8'h57;      // Hiển thị "W" = 0x57
                led_indicators <= 4'b0010;
            end
            pSELECT_PRODUCT: begin 
                if(product_dispense_done) begin
                status_display <= 8'h53;      // "S" = Select
                led_indicators <= 4'b0011;
                end
            end
            pDISPENSE_CHANGE: begin
                if (change_dispense_done) begin
                    status_display <= 8'h43;  // "C" = Change
                    led_indicators <= 4'b0101;
                end
            end
            pRETURN_MONEY: begin
                if (cancel) begin
                    status_display <= 8'h52;  // "R" = Return
                    led_indicators <= 4'b0110;
                end
            end
            default: begin
                status_display <= 8'h2D;      // "-" unknown
                led_indicators <= 4'b1111;
            end
        endcase
    end
end


endmodule

StatusDisplay/status_display_tb.v
`timescale 1ns/1ps
`include "status_display.v"
module status_display_tb;

    // Inputs
    reg clk;
    reg rst_n;
    reg cancel;
    reg display_status_en;
    reg product_dispense_done;
    reg change_dispense_done;
    reg [2:0] state_out;

    // Outputs
    wire [7:0] status_display;
    wire [3:0] led_indicators;

    // Instantiate DUT
    status_display uut (
        .clk(clk),
        .rst_n(rst_n),
        .cancel(cancel),
        .display_status_en(display_status_en),
        .product_dispense_done(product_dispense_done),
        .change_dispense_done(change_dispense_done),
        .state_out(state_out),
        .status_display(status_display),
        .led_indicators(led_indicators)
    );

    // Clock generator
    always #5 clk = ~clk;

    initial begin
        $dumpfile("status_display_tb.vcd");
        $dumpvars(0,status_display_tb);
        // Khởi tạo
        clk = 0;
        rst_n = 0;
        cancel = 0;
        display_status_en = 0;
        product_dispense_done = 0;
        change_dispense_done = 0;
        state_out = 3'b000;

        // Reset
        #10 rst_n = 1;

        // 1. Test trạng thái IDLE
        display_status_en = 1;
        state_out = 3'b000;
        #10;

        // 2. Test trạng thái WAIT_COIN
        state_out = 3'b001;
        #10;

        // 3. Test trạng thái SELECT_PRODUCT (chưa xong)
        state_out = 3'b010;
        product_dispense_done = 0;
        #10;

        // 4. SELECT_PRODUCT với product_dispense_done = 1
        product_dispense_done = 1;
        #10;

        // 5. Test trạng thái DISPENSE_CHANGE (chưa xong)
        state_out = 3'b011;
        change_dispense_done = 0;
        #10;

        // 6. DISPENSE_CHANGE xong
        change_dispense_done = 1;
        #10;

        // 7. Test RETURN_MONEY (không cancel)
        state_out = 3'b100;
        cancel = 0;
        #10;

        // 8. RETURN_MONEY khi cancel = 1
        cancel = 1;
        #30;

        // 9. Vô hiệu hóa display
        display_status_en = 0;
        state_out = 3'b010;
        #10;

        $finish;
    end

endmodule

StatusDisplay/status_display_tb.vcd
$date
	Tue Jun 17 16:10:01 2025
$end
$version
	Icarus Verilog
$end
$timescale
	1ps
$end
$scope module status_display_tb $end
$var wire 8 ! status_display [7:0] $end
$var wire 4 " led_indicators [3:0] $end
$var reg 1 # cancel $end
$var reg 1 $ change_dispense_done $end
$var reg 1 % clk $end
$var reg 1 & display_status_en $end
$var reg 1 ' product_dispense_done $end
$var reg 1 ( rst_n $end
$var reg 3 ) state_out [2:0] $end
$scope module uut $end
$var wire 1 # cancel $end
$var wire 1 $ change_dispense_done $end
$var wire 1 % clk $end
$var wire 1 & display_status_en $end
$var wire 1 ' product_dispense_done $end
$var wire 1 ( rst_n $end
$var wire 3 * state_out [2:0] $end
$var parameter 3 + pDISPENSE_CHANGE $end
$var parameter 3 , pIDLE $end
$var parameter 3 - pRETURN_MONEY $end
$var parameter 3 . pSELECT_PRODUCT $end
$var parameter 3 / pWAIT_COIN $end
$var reg 4 0 led_indicators [3:0] $end
$var reg 8 1 status_display [7:0] $end
$upscope $end
$upscope $end
$enddefinitions $end
$comment Show the parameter values. $end
$dumpall
b1 /
b10 .
b100 -
b0 ,
b11 +
$end
#0
$dumpvars
b0 1
b0 0
b0 *
b0 )
0(
0'
0&
0%
0$
0#
b0 "
b0 !
$end
#5000
1%
#10000
0%
1&
1(
#15000
b1 "
b1 0
b1001001 !
b1001001 1
1%
#20000
0%
b1 )
b1 *
#25000
b10 "
b10 0
b1010111 !
b1010111 1
1%
#30000
0%
b10 )
b10 *
#35000
1%
#40000
0%
1'
#45000
b11 "
b11 0
b1010011 !
b1010011 1
1%
#50000
0%
b11 )
b11 *
#55000
1%
#60000
0%
1$
#65000
b101 "
b101 0
b1000011 !
b1000011 1
1%
#70000
0%
b100 )
b100 *
#75000
1%
#80000
0%
1#
#85000
b0 "
b0 0
b0 !
b0 1
1%
#90000
0%
#95000
1%
#100000
0%
#105000
1%
#110000
0%
b10 )
b10 *
0&
