ChangeCalculator/change_calculator.v
module change_calculator(
    input wire clk,
    input wire rst_n,
    input wire [4:0] current_amount_display,
    input wire [4:0] product_price,
    input wire timeout_flag,
    input wire change_calculator_en,
    output reg [4:0] change_out,
    output reg change_calculator_done
);

    reg [4:0] temp_change_out;

    always @(posedge clk or negedge rst_n) begin
        if (!rst_n) begin
            change_out <= 5'd0;
            change_calculator_done <= 1'b0;
        end else begin
            if (change_calculator_en) begin   
                if(current_amount_display>product_price) begin
                    temp_change_out <= current_amount_display - product_price; 
                    change_calculator_done <= 1'b1;   // bawys dau dem  
                end
            end else if (timeout_flag) begin
                change_out <= temp_change_out;
                change_calculator_done <= 1'b0;   //dem xong
            end
        end
    end

endmodule

ChangeCalculator/change_calculator_tb.v
`timescale 1ns/1ps
`include "change_calculator.v"
module change_calculator_tb;

    // Inputs
    reg clk;
    reg rst_n;
    reg [4:0] current_amount_display;
    reg [4:0] product_price;
    reg timeout_flag;
    reg change_calculator_en;

    // Outputs
    wire [4:0] change_out;
    wire change_calculator_done;

    // Instantiate the Unit Under Test (UUT)
    change_calculator uut (
        .clk(clk),
        .rst_n(rst_n),
        .current_amount_display(current_amount_display),
        .product_price(product_price),
        .timeout_flag(timeout_flag),
        .change_calculator_en(change_calculator_en),
        .change_out(change_out),
        .change_calculator_done(change_calculator_done)
    );

    // Clock generation
    always #5 clk = ~clk; // 10ns clock period

    initial begin
        $dumpfile("change_calculator_tb.vcd");
        $dumpvars(0,change_calculator_tb);
    end


    initial begin
        // Initialize
        clk = 0;
        rst_n = 0;
        current_amount_display = 0;
        product_price = 0;
        timeout_flag = 0;
        change_calculator_en = 0;

        // Reset
        #10 rst_n = 1;

        // === Test case 1: 25 - 15 = 10 ===
        #10;
        current_amount_display = 5'd25;
        product_price = 5'd15;
        change_calculator_en = 1;
        #10;
        change_calculator_en = 0;

        // Wait for timeout
        #10 timeout_flag = 1;
        #10 timeout_flag = 0;

        #20;

        // === Test case 2: 20 - 20 = 0 ===
        current_amount_display = 5'd20;
        product_price = 5'd20;
        change_calculator_en = 1;
        #10;
        change_calculator_en = 0;

        #10 timeout_flag = 1;
        #10 timeout_flag = 0;

        #20;

        // === Test case 3: 30 - 25 = 5 ===
        current_amount_display = 5'd30;
        product_price = 5'd25;
        change_calculator_en = 1;
        #10;
        change_calculator_en = 0;

        #10 timeout_flag = 1;
        #10 timeout_flag = 0;

        #20;

        $finish;
    end

    initial begin
        $display("Time\tCurrent\tPrice\tChange\tDone");
        $monitor("%0dns\t%d\t%d\t%d\t%b", $time, current_amount_display, product_price, change_out, change_calculator_done);
    end

endmodule

ChangeCalculator/change_calculator_tb.vcd
$date
	Wed Jun 18 20:19:56 2025
$end
$version
	Icarus Verilog
$end
$timescale
	1ps
$end
$scope module change_calculator_tb $end
$var wire 5 ! change_out [4:0] $end
$var wire 1 " change_calculator_done $end
$var reg 1 # change_calculator_en $end
$var reg 1 $ clk $end
$var reg 5 % current_amount_display [4:0] $end
$var reg 5 & product_price [4:0] $end
$var reg 1 ' rst_n $end
$var reg 1 ( timeout_flag $end
$scope module uut $end
$var wire 1 # change_calculator_en $end
$var wire 1 $ clk $end
$var wire 5 ) current_amount_display [4:0] $end
$var wire 5 * product_price [4:0] $end
$var wire 1 ' rst_n $end
$var wire 1 ( timeout_flag $end
$var reg 1 " change_calculator_done $end
$var reg 5 + change_out [4:0] $end
$var reg 5 , temp_change_out [4:0] $end
$upscope $end
$upscope $end
$enddefinitions $end
$comment Show the parameter values. $end
$dumpall
$end
#0
$dumpvars
bx ,
b0 +
b0 *
b0 )
0(
0'
b0 &
b0 %
0$
0#
0"
b0 !
$end
#5000
1$
#10000
0$
1'
#15000
1$
#20000
0$
1#
b1111 &
b1111 *
b11001 %
b11001 )
#25000
1"
b1010 ,
1$
#30000
0$
0#
#35000
1$
#40000
0$
1(
#45000
0"
b1010 !
b1010 +
1$
#50000
0$
0(
#55000
1$
#60000
0$
#65000
1$
#70000
0$
1#
b10100 &
b10100 *
b10100 %
b10100 )
#75000
1"
b0 ,
1$
#80000
0$
0#
#85000
1$
#90000
0$
1(
#95000
0"
b0 !
b0 +
1$
#100000
0$
0(
#105000
1$
#110000
0$
#115000
1$
#120000
0$
1#
b11001 &
b11001 *
b11110 %
b11110 )
#125000
1"
b101 ,
1$
#130000
0$
0#
#135000
1$
#140000
0$
1(
#145000
0"
b101 !
b101 +
1$
#150000
0$
0(
