ChangeCalculator/change_calculator.v
module change_calculator(
    input wire clk,
    input wire rst_n,
    input wire [4:0] current_amount_display,
    input wire [4:0] product_price,
    input wire change_dispense_en,
    input wire single_change_calculator,
    output reg [4:0] change_out,
    output reg change_dispense_done
);

    always @(posedge clk or negedge rst_n) begin
        if (!rst_n) begin
            change_out <= 5'd0;
            change_dispense_done <= 1'b0;
        end else begin
            if (single_change_calculator && change_dispense_en) begin
                if (current_amount_display >= product_price) begin
                    change_out <= current_amount_display - product_price;
                    change_dispense_done <= 1'b1;
                end else begin
                    change_out <= 5'd0;
                    change_dispense_done <= 1'b0;
                end
            end else begin
                change_dispense_done <= 1'b0;
            end
        end
    end

endmodule

ChangeCalculator/change_calculator_tb.v
`timescale 1ns / 1ps
`include "change_calculator.v"
module change_calculator_tb;

    // Inputs
    reg clk;
    reg rst_n;
    reg [4:0] current_amount_display;
    reg [4:0] product_price;
    reg change_dispense_en;
    reg single_change_calculator;

    // Outputs
    wire [4:0] change_out;
    wire change_dispense_done;

    // Instantiate the UUT
    change_calculator uut (
        .clk(clk),
        .rst_n(rst_n),
        .current_amount_display(current_amount_display),
        .product_price(product_price),
        .change_dispense_en(change_dispense_en),
        .single_change_calculator(single_change_calculator),
        .change_out(change_out),
        .change_dispense_done(change_dispense_done)
    );

    // Clock generation
    always #5 clk = ~clk;  // 10ns period

    // Task to run a single test case
        task run_test(
        input [4:0] money,
        input [4:0] price,
        input [127:0] desc  // dùng reg kiểu vector thay cho string
    );
        begin
            $display("=== %s ===", desc);
            current_amount_display = money;
            product_price = price;
            single_change_calculator = 1;
            change_dispense_en = 1;
            #10;

            change_dispense_en = 1;
            #10;

            change_dispense_en = 0;
            single_change_calculator = 0;
            #10;

            $display("Time: %0t | Input: %0d - %0d | Change: %0d | Done: %b\n",
                $time, money, price, change_out, change_dispense_done);
        end
    endtask


    // Initial block
    initial begin
        // Optional: waveform
        $dumpfile("change_calculator_tb.vcd");
        $dumpvars(0, change_calculator_tb);

        // Reset and init
        clk = 0;
        rst_n = 0;
        current_amount_display = 0;
        product_price = 0;
        change_dispense_en = 0;
        single_change_calculator = 0;

        #20 rst_n = 1;

        // Run tests
        run_test(5'd20, 5'd15, "Test 1: Enough money, should return 5");
        run_test(5'd25, 5'd5,  "Test 2: Large change, should return 20");
        run_test(5'd10, 5'd10, "Test 3: Exact amount, should return 0");
        run_test(5'd8,  5'd10, "Test 4: Not enough money, return 0");

        #20;
        $finish;
    end

endmodule

ChangeCalculator/change_calculator_tb.vcd
$date
	Tue Jun 17 10:01:51 2025
$end
$version
	Icarus Verilog
$end
$timescale
	1ps
$end
$scope module change_calculator_tb $end
$var wire 5 ! change_out [4:0] $end
$var wire 1 " change_dispense_done $end
$var reg 1 # change_dispense_en $end
$var reg 1 $ clk $end
$var reg 5 % current_amount_display [4:0] $end
$var reg 5 & product_price [4:0] $end
$var reg 1 ' rst_n $end
$var reg 1 ( single_change_calculator $end
$scope module uut $end
$var wire 1 # change_dispense_en $end
$var wire 1 $ clk $end
$var wire 5 ) current_amount_display [4:0] $end
$var wire 5 * product_price [4:0] $end
$var wire 1 ' rst_n $end
$var wire 1 ( single_change_calculator $end
$var reg 1 " change_dispense_done $end
$var reg 5 + change_out [4:0] $end
$upscope $end
$scope task run_test $end
$var reg 128 , desc [127:0] $end
$var reg 5 - money [4:0] $end
$var reg 5 . price [4:0] $end
$upscope $end
$upscope $end
$enddefinitions $end
$comment Show the parameter values. $end
$dumpall
$end
#0
$dumpvars
bx .
bx -
bx ,
b0 +
b0 *
b0 )
0(
0'
b0 &
b0 %
0$
0#
0"
b0 !
$end
#5000
1$
#10000
0$
#15000
1$
#20000
0$
1#
1(
b1111 &
b1111 *
b10100 %
b10100 )
b100000011100110110100001101111011101010110110001100100001000000111001001100101011101000111010101110010011011100010000000110101 ,
b1111 .
b10100 -
1'
#25000
1"
b101 !
b101 +
1$
#30000
0$
#35000
1$
#40000
0$
0(
0#
#45000
0"
1$
#50000
0$
1#
1(
b101 &
b101 *
b11001 %
b11001 )
b1110011011010000110111101110101011011000110010000100000011100100110010101110100011101010111001001101110001000000011001000110000 ,
b101 .
b11001 -
#55000
1"
b10100 !
b10100 +
1$
#60000
0$
#65000
1$
#70000
0$
0(
0#
#75000
0"
1$
#80000
0$
1#
1(
b1010 &
b1010 *
b1010 %
b1010 )
b100000011100110110100001101111011101010110110001100100001000000111001001100101011101000111010101110010011011100010000000110000 ,
b1010 .
b1010 -
#85000
1"
b0 !
b0 +
1$
#90000
0$
#95000
1$
#100000
0$
0(
0#
#105000
0"
1$
#110000
0$
1#
1(
b1000 %
b1000 )
b100000011011010110111101101110011001010111100100101100001000000111001001100101011101000111010101110010011011100010000000110000 ,
b1000 -
#115000
1$
#120000
0$
#125000
1$
#130000
0$
0(
0#
