VendingMachine/total_amount.v
module total_amount(
    input wire clk,
    input wire rst_n,
    input wire cancel,
    input wire [4:0] coin_value,
    input wire coin_valid,
    input wire [1:0] product_sel,
    input wire timeout_flag,

    output reg [4:0] current_amount,
    output reg total_amount_done,
    output reg coin_value_in
);

    reg [4:0] temp_current_amount;

    always @(posedge clk or negedge rst_n) begin
        if (!rst_n || cancel) begin
            temp_current_amount <= 5'd0;
            current_amount      <= 5'd0;
            total_amount_done   <= 1'b0;
            coin_value_in       <= 1'b0;
        end else begin
            if (coin_valid) begin
                temp_current_amount <= temp_current_amount + coin_value;
                coin_value_in <= 1'b1;
            end else begin
                coin_value_in <= 1'b0;
            end

            if (product_sel != 2'b00 && timeout_flag) begin
                current_amount <= temp_current_amount;
                total_amount_done <= 1'b1;
            end else if (timeout_flag) begin
                temp_current_amount <= 5'd0;
                current_amount <= 5'd0;
                total_amount_done <= 1'b0;
            end else begin
                total_amount_done <= 1'b0;
            end
        end
    end

endmodule

TotalAmount/total_amount_tb.v
`timescale 1ns/1ps
`include "total_amount.v"
module total_amount_tb;

    // Inputs
    reg clk, rst_n, cancel, coin_valid, timeout_flag;
    reg [4:0] coin_value;
    reg [1:0] product_sel;

    // Outputs
    wire [4:0] current_amount;
    wire total_amount_done;
    wire coin_value_in;

    // Instantiate the total_amount module
    total_amount uut (
        .clk(clk),
        .rst_n(rst_n),
        .cancel(cancel),
        .coin_value(coin_value),
        .coin_valid(coin_valid),
        .product_sel(product_sel),
        .timeout_flag(timeout_flag),
        .current_amount(current_amount),
        .total_amount_done(total_amount_done),
        .coin_value_in(coin_value_in)
    );

    // Clock generation
    always #5 clk = ~clk; // 10ns period

    initial begin
        $dumpfile("total_amount_tb.vcd");
        $dumpvars(0,total_amount_tb);
    end


    initial begin
        // Initial values
        clk = 0;
        rst_n = 0;
        cancel = 0;
        coin_value = 5'd0;
        coin_valid = 0;
        product_sel = 2'b00;
        timeout_flag = 0;

        // Reset
        #12; rst_n = 1;

        // --- Test 1: Insert 5đ ---
        #10; coin_value = 5'd5; coin_valid = 1;
        #10; coin_valid = 0;

        // --- Test 2: Insert 10đ ---
        #10; coin_value = 5'd10; coin_valid = 1;
        #10; coin_valid = 0;

        // --- Test 3: Insert 1đ ---
        #10; coin_value = 5'd1; coin_valid = 1;
        #10; coin_valid = 0;

        // --- Test 4: Select product ---
        #10; product_sel = 2'b01;
       

        // --- Test 5: Timeout ---
        #10; timeout_flag = 1;
        #10; timeout_flag = 0;

        // --- Test 6: Cancel ---
        #10; cancel = 1;
        #10; cancel = 0;

        #20;
        $finish;
    end

    initial begin
        $monitor("T=%0t | coin_value=%2d | coin_valid=%b | coin_value_in=%b | temp_amt=%2d | curr_amt=%2d | done=%b | product_sel=%b | cancel=%b | timeout=%b",
                 $time, coin_value, coin_valid, coin_value_in,
                 uut.temp_current_amount,
                 current_amount, total_amount_done,
                 product_sel, cancel, timeout_flag);
    end

endmodule

TotalAmount/total_amount_tb.vcd
$date
	Fri Jun 20 12:55:40 2025
$end
$version
	Icarus Verilog
$end
$timescale
	1ps
$end
$scope module total_amount_tb $end
$var wire 1 ! total_amount_done $end
$var wire 5 " current_amount [4:0] $end
$var wire 1 # coin_value_in $end
$var reg 1 $ cancel $end
$var reg 1 % clk $end
$var reg 1 & coin_valid $end
$var reg 5 ' coin_value [4:0] $end
$var reg 2 ( product_sel [1:0] $end
$var reg 1 ) rst_n $end
$var reg 1 * timeout_flag $end
$scope module uut $end
$var wire 1 $ cancel $end
$var wire 1 % clk $end
$var wire 1 & coin_valid $end
$var wire 5 + coin_value [4:0] $end
$var wire 2 , product_sel [1:0] $end
$var wire 1 ) rst_n $end
$var wire 1 * timeout_flag $end
$var reg 1 # coin_value_in $end
$var reg 5 - current_amount [4:0] $end
$var reg 5 . temp_current_amount [4:0] $end
$var reg 1 ! total_amount_done $end
$upscope $end
$upscope $end
$enddefinitions $end
$comment Show the parameter values. $end
$dumpall
$end
#0
$dumpvars
b0 .
b0 -
b0 ,
b0 +
0*
0)
b0 (
b0 '
0&
0%
0$
0#
b0 "
0!
$end
#5000
1%
#10000
0%
#12000
1)
#15000
1%
#20000
0%
#22000
1&
b101 '
b101 +
#25000
1#
b101 .
1%
#30000
0%
#32000
0&
#35000
0#
1%
#40000
0%
#42000
1&
b1010 '
b1010 +
#45000
1#
b1111 .
1%
#50000
0%
#52000
0&
#55000
0#
1%
#60000
0%
#62000
1&
b1 '
b1 +
#65000
1#
b10000 .
1%
#70000
0%
#72000
0&
#75000
0#
1%
#80000
0%
#82000
b1 (
b1 ,
#85000
1%
#90000
0%
#92000
1*
#95000
1!
b10000 "
b10000 -
1%
#100000
0%
#102000
0*
#105000
0!
1%
#110000
0%
#112000
1$
#115000
b0 "
b0 -
b0 .
1%
#120000
0%
#122000
0$
