TotalAmount/total_amount.v
module total_amount(
    input wire clk,
    input wire rst_n,
    input wire cancel, // 1đ, 5đ, 10đ
    input wire [4:0] coin_value, 
    output reg [4:0] current_amount
);

    always @(posedge clk or negedge rst_n) begin
        if (!rst_n || cancel) begin
            current_amount <= 5'd0;
        end else begin
            current_amount <= current_amount + coin_value; // Update current amount with new coin value
        end
    end
   
endmodule

TotalAmount/total_amount_tb.v
`timescale 1ns/1ps
`include "total_amount.v"

module total_amount_tb;

    reg clk;
    reg rst_n;
    reg cancel;
    reg [4:0] coin_value;
    wire [4:0] current_amount;


    // Instantiate the total_amount module
    total_amount uut (
        .clk(clk),
        .rst_n(rst_n),
        .cancel(cancel),
        .coin_value(coin_value),
        .current_amount(current_amount)
    );

    // Clock generation
    initial begin
        clk = 0;
        forever #5 clk = ~clk; // 10 ns clock period
    end

    initial begin
        $dumpfile("total_amount_tb.vcd");
        $dumpvars(0, total_amount_tb);
    end

    // Display monitor
    initial begin
        $display("Time\tclk\trst_n\tcancel\tcoin_value\tcurrent_amount");
        $monitor("%4dns\t%b\t%b\t%b\t%2d\t\t%2d",
                 $time, clk, rst_n, cancel, coin_value, current_amount);
    end

    // Test sequence
    initial begin
        rst_n = 0; // Reset the system
        cancel = 0;
        coin_value = 5'd0;

        #10 rst_n = 1; // Release reset

        // Test adding coins
        coin_value = 5'd1; // Add 1đ
        #10;

        coin_value = 5'd5; // Add 5đ
        #10;

        coin_value = 5'd10; // Add 10đ
        #10;

        // Test cancel operation
        cancel = 1; // Trigger cancel
        #10;
        
        cancel = 0; // Release cancel

        // Add more coins after cancel
        coin_value = 5'd2; // Add 2đ
        #10;

        coin_value = 5'd3; // Add 3đ
        #10;

        $finish; // End simulation
    end
endmodule

TotalAmount/total_amount_tb.vcd
$date
	Mon Jun 16 09:00:15 2025
$end
$version
	Icarus Verilog
$end
$timescale
	1ps
$end
$scope module total_amount_tb $end
$var wire 5 ! current_amount [4:0] $end
$var reg 1 " cancel $end
$var reg 1 # clk $end
$var reg 5 $ coin_value [4:0] $end
$var reg 1 % rst_n $end
$scope module uut $end
$var wire 1 " cancel $end
$var wire 1 # clk $end
$var wire 5 & coin_value [4:0] $end
$var wire 1 % rst_n $end
$var reg 5 ' current_amount [4:0] $end
$upscope $end
$upscope $end
$enddefinitions $end
$comment Show the parameter values. $end
$dumpall
$end
#0
$dumpvars
b0 '
b0 &
0%
b0 $
0#
0"
b0 !
$end
#5000
1#
#10000
0#
b1 $
b1 &
1%
#15000
b1 !
b1 '
1#
#20000
0#
b101 $
b101 &
#25000
b110 !
b110 '
1#
#30000
0#
b1010 $
b1010 &
#35000
b10000 !
b10000 '
1#
#40000
0#
1"
#45000
b0 !
b0 '
1#
#50000
0#
b10 $
b10 &
0"
#55000
b10 !
b10 '
1#
#60000
0#
b11 $
b11 &
#65000
b101 !
b101 '
1#
