AmountCounter/amount_counter.v
module amount_counter(
    input wire clk,
    input wire rst_n,
    input wire cancel, // Nút hủy
    input wire [4:0] current_amount, // 1đ, 5đ, 10đ
    input wire [4:0] product_price,
    output reg enough_money
);

    always @(posedge clk or negedge rst_n) begin
        if (!rst_n || cancel) begin
            enough_money <= 1'b0; // Reset cờ đủ tiền
        end else begin
            if (current_amount >= product_price) begin
                enough_money <= 1'b1; // Đủ tiền
            end else begin
                enough_money <= 1'b0; // Không đủ tiền
            end
        end
    end
   
endmodule

AmountCounter/amount_counter_tb.v
`timescale 1ns/1ps
`include "amount_counter.v"
module amount_counter_tb;

    // Khai báo tín hiệu kết nối với DUT
    reg clk;
    reg rst_n;
    reg cancel;
    reg [4:0] current_amount;
    reg [4:0] product_price;
    wire enough_money;

    // Khởi tạo module cần test (DUT)
    amount_counter uut (
        .clk(clk),
        .rst_n(rst_n),
        .cancel(cancel),
        .current_amount(current_amount),
        .product_price(product_price),
        .enough_money(enough_money)
    );

    // Tạo xung clock 10ns (tần số 100MHz)
    always #5 clk = ~clk;

    initial begin
        $display("=== BẮT ĐẦU TEST amount_counter ===");
        $dumpfile("amount_counter_tb.vcd");
        $dumpvars(0, amount_counter_tb);

        // Khởi tạo các giá trị ban đầu
        clk = 0;
        rst_n = 0;
        cancel = 0;
        current_amount = 5'd0;
        product_price = 5'd10; // Sản phẩm giá 10đ

        // Reset hệ thống
        #10;
        rst_n = 1;

        // Test 1: current_amount = 5 -> chưa đủ
        #10;
        current_amount = 5;
        #10;
        $display("Test 1: current_amount = %d, product_price = %d, enough_money = %b (expect 0)",
                 current_amount, product_price, enough_money);

        // Test 2: current_amount = 10 -> đủ tiền
        #10;
        current_amount = 10;
        #10;
        $display("Test 2: current_amount = %d, product_price = %d, enough_money = %b (expect 1)",
                 current_amount, product_price, enough_money);

        // Test 3: current_amount = 15 -> đủ tiền
        #10;
        current_amount = 15;
        #10;
        $display("Test 3: current_amount = %d, product_price = %d, enough_money = %b (expect 1)",
                 current_amount, product_price, enough_money);

        // Test 4: cancel = 1 -> dù có đủ tiền cũng phải reset cờ
        #10;
        cancel = 1;
        #10;
        $display("Test 4: CANCEL -> enough_money = %b (expect 0)", enough_money);
        cancel = 0;

        // Test 5: Reset hệ thống
        #10;
        rst_n = 0;
        #10;
        rst_n = 1;
        #10;
        $display("Test 5: RESET -> enough_money = %b (expect 0)", enough_money);

        #10;
        $display("=== KẾT THÚC TEST ===");
        $finish;
    end

endmodule

AmountCounter/amount_counter_tb.vcd
$date
	Mon Jun 16 09:04:11 2025
$end
$version
	Icarus Verilog
$end
$timescale
	1ps
$end
$scope module amount_counter_tb $end
$var wire 1 ! enough_money $end
$var reg 1 " cancel $end
$var reg 1 # clk $end
$var reg 5 $ current_amount [4:0] $end
$var reg 5 % product_price [4:0] $end
$var reg 1 & rst_n $end
$scope module uut $end
$var wire 1 " cancel $end
$var wire 1 # clk $end
$var wire 5 ' current_amount [4:0] $end
$var wire 5 ( product_price [4:0] $end
$var wire 1 & rst_n $end
$var reg 1 ! enough_money $end
$upscope $end
$upscope $end
$enddefinitions $end
$comment Show the parameter values. $end
$dumpall
$end
#0
$dumpvars
b1010 (
b0 '
0&
b1010 %
b0 $
0#
0"
0!
$end
#5000
1#
#10000
0#
1&
#15000
1#
#20000
0#
b101 $
b101 '
#25000
1#
#30000
0#
#35000
1#
#40000
0#
b1010 $
b1010 '
#45000
1!
1#
#50000
0#
#55000
1#
#60000
0#
b1111 $
b1111 '
#65000
1#
#70000
0#
#75000
1#
#80000
0#
1"
#85000
0!
1#
#90000
0#
0"
#95000
1!
1#
#100000
0!
0#
0&
#105000
1#
#110000
0#
1&
#115000
1!
1#
