Product/product_selector.v
module product_selector #(
    parameter PRODUCT_A_PRICE = 5'd15, 
    parameter PRODUCT_B_PRICE = 5'd20, 
    parameter PRODUCT_C_PRICE = 5'd25
)(
    input wire clk,
    input wire rst_n,
    input wire [1:0] product_sel,
    input wire product_dispense_en,
    input wire signal_product_selector,
    output reg [4:0] product_price,
    output reg [1:0] product_out,
    output reg product_dispense_done,
    output reg product_selector_done
);

    parameter PRODUCT_A = 2'b01;
    parameter PRODUCT_B = 2'b10;
    parameter PRODUCT_C = 2'b11;

    reg [4:0] temp_product_price;
    reg [1:0] temp_product_out;

    always @(posedge clk or negedge rst_n) begin
        if (!rst_n) begin
            product_price <= 5'd0;
            product_out <= 2'b00;
            product_dispense_done <= 1'b0;
            product_selector_done <= 1'b0;
        end else begin
            if (signal_product_selector) begin
                case (product_sel)
                    PRODUCT_A: begin
                        temp_product_price <= PRODUCT_A_PRICE;
                        temp_product_out <= PRODUCT_A;
                        product_selector_done <= 1'b1;
                    end
                    PRODUCT_B: begin
                        temp_product_price <= PRODUCT_B_PRICE;
                        temp_product_out <= PRODUCT_B;
                        product_selector_done <= 1'b1;
                    end
                    PRODUCT_C: begin
                        temp_product_price <= PRODUCT_C_PRICE;
                        temp_product_out <= PRODUCT_C;
                        product_selector_done <= 1'b1;
                    end
                    default: begin
                        temp_product_price <= 5'd0;
                        temp_product_out <= 2'b00;
                        product_selector_done <= 1'b0;
                    end
                endcase
            end else begin
                temp_product_price <= 5'd0;
                temp_product_out <= 2'b00;
            end

            if (product_dispense_en) begin
                product_price <= temp_product_price;
                product_out <= temp_product_out;
                product_dispense_done <= 1'b1;
            end 
            else begin
                product_price <= 5'd0;
                product_out <= 2'b00;
            end 
        end
    end

endmodule

Product/product_selector_tb.v
`timescale 1ns/1ps
`include "product_selector.v"
module product_selector_tb;

    // Inputs
    reg clk;
    reg rst_n;
    reg [1:0] product_sel;
    reg product_dispense_en;
    reg signal_product_selector;

    // Outputs
    wire [4:0] product_price;
    wire [1:0] product_out;
    wire product_dispense_done;
    wire product_selector_done;

    // Instantiate the DUT
    product_selector uut (
        .clk(clk),
        .rst_n(rst_n),
        .product_sel(product_sel),
        .product_dispense_en(product_dispense_en),
        .signal_product_selector(signal_product_selector),
        .product_price(product_price),
        .product_out(product_out),
        .product_dispense_done(product_dispense_done),
        .product_selector_done(product_selector_done)
    );

    // Clock generation
    always #5 clk = ~clk; // 10ns period

    // Task for product selection test
    task select_product(input [1:0] sel);
        begin
            product_sel = sel;
            signal_product_selector = 1;
            #10;
            signal_product_selector = 0;
            product_dispense_en = 1;
            #10;
            product_dispense_en = 0;
        end
    endtask

    initial begin
        $dumpfile("product_selector_tb.vcd");
        $dumpvars(0,product_selector_tb);

    end


    initial begin
        
        $display("=== Starting product_selector test ===");
        
        // Initialize
        clk = 0;
        rst_n = 0;
        product_sel = 2'b00;
        product_dispense_en = 0;
        signal_product_selector = 0;

        // Reset pulse
        #10 rst_n = 1;

        // Test PRODUCT_A: 2'b01
        #10;
        $display("Selecting PRODUCT_A");
        select_product(2'b01);
        #10;

        // // Test PRODUCT_B: 2'b10
        // $display("Selecting PRODUCT_B");
        // select_product(2'b10);
        // #10;

        // // Test PRODUCT_C: 2'b11
        // $display("Selecting PRODUCT_C");
        // select_product(2'b11);
        // #10;

        // Test invalid input: 2'b00
        $display("Selecting INVALID PRODUCT");
        select_product(2'b00);
        #10;

        $display("=== Simulation complete ===");
        $finish;
    end

endmodule

Product/product_selector_tb.vcd
$date
	Tue Jun 17 21:44:35 2025
$end
$version
	Icarus Verilog
$end
$timescale
	1ps
$end
$scope module product_selector_tb $end
$var wire 1 ! product_selector_done $end
$var wire 5 " product_price [4:0] $end
$var wire 2 # product_out [1:0] $end
$var wire 1 $ product_dispense_done $end
$var reg 1 % clk $end
$var reg 1 & product_dispense_en $end
$var reg 2 ' product_sel [1:0] $end
$var reg 1 ( rst_n $end
$var reg 1 ) signal_product_selector $end
$scope module uut $end
$var wire 1 % clk $end
$var wire 1 & product_dispense_en $end
$var wire 2 * product_sel [1:0] $end
$var wire 1 ( rst_n $end
$var wire 1 ) signal_product_selector $end
$var parameter 2 + PRODUCT_A $end
$var parameter 5 , PRODUCT_A_PRICE $end
$var parameter 2 - PRODUCT_B $end
$var parameter 5 . PRODUCT_B_PRICE $end
$var parameter 2 / PRODUCT_C $end
$var parameter 5 0 PRODUCT_C_PRICE $end
$var reg 1 $ product_dispense_done $end
$var reg 2 1 product_out [1:0] $end
$var reg 5 2 product_price [4:0] $end
$var reg 1 ! product_selector_done $end
$var reg 2 3 temp_product_out [1:0] $end
$var reg 5 4 temp_product_price [4:0] $end
$upscope $end
$scope task select_product $end
$var reg 2 5 sel [1:0] $end
$upscope $end
$upscope $end
$enddefinitions $end
$comment Show the parameter values. $end
$dumpall
b11001 0
b11 /
b10100 .
b10 -
b1111 ,
b1 +
$end
#0
$dumpvars
bx 5
bx 4
bx 3
b0 2
b0 1
b0 *
0)
0(
b0 '
0&
0%
0$
b0 #
b0 "
0!
$end
#5000
1%
#10000
0%
1(
#15000
b0 3
b0 4
1%
#20000
0%
1)
b1 '
b1 *
b1 5
#25000
1!
b1 3
b1111 4
1%
#30000
0%
1&
0)
#35000
1$
b1 #
b1 1
b1111 "
b1111 2
b0 3
b0 4
1%
#40000
0%
0&
#45000
b0 #
b0 1
b0 "
b0 2
1%
#50000
0%
1)
b0 '
b0 *
b0 5
#55000
0!
1%
#60000
0%
1&
0)
#65000
1%
#70000
0%
0&
