VendingMachine/timer.v
module timer #(
    parameter TIME_WAIT_SELECT    = 30,
    parameter TIME_PRODUCT_RETURN = 5,
    parameter TIME_CHANGE_RETURN  = 5
)(
    input wire clk,
    input wire rst_n,
    input wire [1:0] start_timer,   // Chế độ timer
    output reg timeout_flag
);

    // Các chế độ
    localparam WAIT_SELECT    = 2'b01;
    localparam PRODUCT_RETURN = 2'b10;
    localparam CHANGE_RETURN  = 2'b11;

    reg [4:0] counter;
    reg running;
    reg [1:0] prev_timer;

    always @(posedge clk or negedge rst_n) begin
        if (!rst_n) begin
            counter <= 5'd0;
            timeout_flag <= 1'b0;
            running <= 1'b0;
            prev_timer <= 2'b00;
        end else begin
            if (start_timer != prev_timer && start_timer != 2'b00) begin
                // Chuyển sang chế độ mới
                case (start_timer)
                    WAIT_SELECT:    counter <= TIME_WAIT_SELECT;
                    PRODUCT_RETURN: counter <= TIME_PRODUCT_RETURN;
                    CHANGE_RETURN:  counter <= TIME_CHANGE_RETURN;
                    default:        counter <= 0;
                endcase
                timeout_flag <= 1'b0;
                running <= 1'b1;
                prev_timer <= start_timer;
            end else if (running) begin
                if (counter > 0) begin
                    counter <= counter - 1;
                    timeout_flag <= 1'b0;
                end else begin
                    timeout_flag <= 1'b1;
                    running <= 1'b0;
                end
            end
        end
    end

endmodule

Timer/timer_tb.v
`timescale 1ns/1ps
`include "timer.v"
module timer_tb;

    reg clk;
    reg rst_n;
    reg [1:0] start_timer;
    wire timeout_flag;

    // Instantiate timer
    timer uut (
        .clk(clk),
        .rst_n(rst_n),
        .start_timer(start_timer),
        .timeout_flag(timeout_flag)
    );

    // Clock generation
    initial clk = 0;
    always #5 clk = ~clk; // 10ns period

    initial begin
        $dumpfile("timer_tb.vcd");
        $dumpvars(0, timer_tb);

        // Khởi tạo
        rst_n = 0;
        start_timer = 2'b00;
        #20;
        rst_n = 1;

        // Test chế độ WAIT_SELECT
        @(negedge clk);
        start_timer = 2'b01; // WAIT_SELECT
        @(negedge clk);
        start_timer = 2'b00;

        wait(timeout_flag == 1);
        $display("WAIT_SELECT timeout at time %t", $time);

        // Test chế độ PRODUCT_RETURN
        @(negedge clk);
        start_timer = 2'b10;
        @(negedge clk);
        start_timer = 2'b00;

        wait(timeout_flag == 1);
        $display("PRODUCT_RETURN timeout at time %t", $time);

        // Test chế độ CHANGE_RETURN
        @(negedge clk);
        start_timer = 2'b11;
        @(negedge clk);
        start_timer = 2'b00;

        wait(timeout_flag == 1);
        $display("CHANGE_RETURN timeout at time %t", $time);

        $finish;
    end

endmodule

Timer/timer_tb.vcd
$date
	Fri Jun 20 12:37:33 2025
$end
$version
	Icarus Verilog
$end
$timescale
	1ps
$end
$scope module timer_tb $end
$var wire 1 ! timeout_flag $end
$var reg 1 " clk $end
$var reg 1 # rst_n $end
$var reg 2 $ start_timer [1:0] $end
$scope module uut $end
$var wire 1 " clk $end
$var wire 1 # rst_n $end
$var wire 2 % start_timer [1:0] $end
$var parameter 2 & CHANGE_RETURN $end
$var parameter 2 ' PRODUCT_RETURN $end
$var parameter 32 ( TIME_CHANGE_RETURN $end
$var parameter 32 ) TIME_PRODUCT_RETURN $end
$var parameter 32 * TIME_WAIT_SELECT $end
$var parameter 2 + WAIT_SELECT $end
$var reg 5 , counter [4:0] $end
$var reg 2 - prev_timer [1:0] $end
$var reg 1 . running $end
$var reg 1 ! timeout_flag $end
$upscope $end
$upscope $end
$enddefinitions $end
$comment Show the parameter values. $end
$dumpall
b1 +
b11110 *
b101 )
b101 (
b10 '
b11 &
$end
#0
$dumpvars
0.
b0 -
b0 ,
b0 %
b0 $
0#
0"
0!
$end
#5000
1"
#10000
0"
#15000
1"
#20000
b1 $
b1 %
0"
1#
#25000
b1 -
1.
b11110 ,
1"
#30000
b0 $
b0 %
0"
#35000
b11101 ,
1"
#40000
0"
#45000
b11100 ,
1"
#50000
0"
#55000
b11011 ,
1"
#60000
0"
#65000
b11010 ,
1"
#70000
0"
#75000
b11001 ,
1"
#80000
0"
#85000
b11000 ,
1"
#90000
0"
#95000
b10111 ,
1"
#100000
0"
#105000
b10110 ,
1"
#110000
0"
#115000
b10101 ,
1"
#120000
0"
#125000
b10100 ,
1"
#130000
0"
#135000
b10011 ,
1"
#140000
0"
#145000
b10010 ,
1"
#150000
0"
#155000
b10001 ,
1"
#160000
0"
#165000
b10000 ,
1"
#170000
0"
#175000
b1111 ,
1"
#180000
0"
#185000
b1110 ,
1"
#190000
0"
#195000
b1101 ,
1"
#200000
0"
#205000
b1100 ,
1"
#210000
0"
#215000
b1011 ,
1"
#220000
0"
#225000
b1010 ,
1"
#230000
0"
#235000
b1001 ,
1"
#240000
0"
#245000
b1000 ,
1"
#250000
0"
#255000
b111 ,
1"
#260000
0"
#265000
b110 ,
1"
#270000
0"
#275000
b101 ,
1"
#280000
0"
#285000
b100 ,
1"
#290000
0"
#295000
b11 ,
1"
#300000
0"
#305000
b10 ,
1"
#310000
0"
#315000
b1 ,
1"
#320000
0"
#325000
b0 ,
1"
#330000
0"
#335000
0.
1!
1"
#340000
b10 $
b10 %
0"
#345000
b10 -
1.
0!
b101 ,
1"
#350000
b0 $
b0 %
0"
#355000
b100 ,
1"
#360000
0"
#365000
b11 ,
1"
#370000
0"
#375000
b10 ,
1"
#380000
0"
#385000
b1 ,
1"
#390000
0"
#395000
b0 ,
1"
#400000
0"
#405000
0.
1!
1"
#410000
b11 $
b11 %
0"
#415000
b11 -
1.
0!
b101 ,
1"
#420000
b0 $
b0 %
0"
#425000
b100 ,
1"
#430000
0"
#435000
b11 ,
1"
#440000
0"
#445000
b10 ,
1"
#450000
0"
#455000
b1 ,
1"
#460000
0"
#465000
b0 ,
1"
#470000
0"
#475000
0.
1!
1"
