Timer/timer.v
module timer #(
    parameter TIME_WAIT_SELECT   = 5'd30,
    parameter TIME_PRODUCT_RETURN = 5'd5,
    parameter TIME_CHANGE_RETURN  = 5'd5
)(
    input wire clk,
    input wire rst_n,
    input wire [1:0] start_timer,
    output reg timeout_flag,
    output reg [4:0] debug_counter  // Để debug hoặc kiểm tra testbench
);

    // Các chế độ
    localparam WAIT_SELECT   = 2'b00;
    localparam PRODUCT_RETURN = 2'b01;
    localparam CHANGE_RETURN  = 2'b10;

    reg [4:0] counter;
    reg running;
    reg [1:0] prev_mode;

    always @(posedge clk or negedge rst_n) begin
        if (!rst_n) begin
            counter <= 5'd0;
            timeout_flag <= 1'b0;
            running <= 1'b0;
            prev_mode <= 2'b11;
            debug_counter <= 5'd0;
        end else begin
            if (start_timer != prev_mode) begin
                // Chuyển sang chế độ mới
                case (start_timer)
                    WAIT_SELECT:      counter <= TIME_WAIT_SELECT;
                    PRODUCT_RETURN:   counter <= TIME_PRODUCT_RETURN;
                    CHANGE_RETURN:    counter <= TIME_CHANGE_RETURN;
                    default:          counter <= 5'd0;
                endcase
                timeout_flag <= 1'b0;
                running <= 1'b1;
                prev_mode <= start_timer;
            end else if (running) begin
                if (counter > 0) begin
                    counter <= counter - 1;
                    timeout_flag <= 1'b0;
                end else begin
                    timeout_flag <= 1'b1;
                    running <= 1'b0;
                end
            end
            debug_counter <= counter;
        end
    end

endmodule

Timer/timer_tb.v
`timescale 1ns / 1ps
`include "timer.v"
module timer_tb;

    // Parameters để test nhanh
    parameter TIME_WAIT_SELECT   = 5'd10;
    parameter TIME_PRODUCT_RETURN = 5'd4;
    parameter TIME_CHANGE_RETURN  = 5'd3;

    // Inputs
    reg clk;
    reg rst_n;
    reg [1:0] start_timer;

    // Outputs
    wire timeout_flag;
    wire [4:0] debug_counter;

    // Instantiate the Unit Under Test
    timer #(
        .TIME_WAIT_SELECT(TIME_WAIT_SELECT),
        .TIME_PRODUCT_RETURN(TIME_PRODUCT_RETURN),
        .TIME_CHANGE_RETURN(TIME_CHANGE_RETURN)
    ) uut (
        .clk(clk),
        .rst_n(rst_n),
        .start_timer(start_timer),
        .timeout_flag(timeout_flag),
        .debug_counter(debug_counter)
    );

    // Clock: 10ns period
    always #5 clk = ~clk;

    // Task để test chế độ
    task test_mode(input [1:0] mode, input [4:0] wait_time);
        integer i;
        begin
            start_timer = mode;
            #10; // chờ 1 chu kỳ để load counter
            for (i = 0; i <= wait_time + 2; i = i + 1) begin
                #10;
                $display("Time: %0t | Mode: %b | Counter: %2d | Timeout: %b", 
                    $time, start_timer, debug_counter, timeout_flag);
            end
            $display("=== Done Testing Mode %b ===\n", mode);
        end
    endtask

    initial begin
        // Ghi waveform nếu cần
        $dumpfile("timer_tb.vcd");
        $dumpvars(0, timer_tb);

        // Khởi tạo
        clk = 0;
        rst_n = 0;
        start_timer = 2'b00;

        #20 rst_n = 1;

        // Test từng chế độ
        test_mode(2'b00, TIME_WAIT_SELECT);     // WAIT_SELECT
        test_mode(2'b01, TIME_PRODUCT_RETURN);  // PRODUCT_RETURN
        test_mode(2'b10, TIME_CHANGE_RETURN);   // CHANGE_RETURN

        // Kết thúc mô phỏng
        $finish;

    end

endmodule

Timer/timer_tb.vcd
$date
	Tue Jun 17 08:26:27 2025
$end
$version
	Icarus Verilog
$end
$timescale
	1ps
$end
$scope module timer_tb $end
$var wire 1 ! timeout_flag $end
$var wire 5 " debug_counter [4:0] $end
$var parameter 5 # TIME_CHANGE_RETURN $end
$var parameter 5 $ TIME_PRODUCT_RETURN $end
$var parameter 5 % TIME_WAIT_SELECT $end
$var reg 1 & clk $end
$var reg 1 ' rst_n $end
$var reg 2 ( start_timer [1:0] $end
$scope module uut $end
$var wire 1 & clk $end
$var wire 1 ' rst_n $end
$var wire 2 ) start_timer [1:0] $end
$var parameter 2 * CHANGE_RETURN $end
$var parameter 2 + PRODUCT_RETURN $end
$var parameter 5 , TIME_CHANGE_RETURN $end
$var parameter 5 - TIME_PRODUCT_RETURN $end
$var parameter 5 . TIME_WAIT_SELECT $end
$var parameter 2 / WAIT_SELECT $end
$var reg 5 0 counter [4:0] $end
$var reg 5 1 debug_counter [4:0] $end
$var reg 2 2 prev_mode [1:0] $end
$var reg 1 3 running $end
$var reg 1 ! timeout_flag $end
$upscope $end
$scope task test_mode $end
$var reg 2 4 mode [1:0] $end
$var reg 5 5 wait_time [4:0] $end
$var integer 32 6 i [31:0] $end
$upscope $end
$upscope $end
$enddefinitions $end
$comment Show the parameter values. $end
$dumpall
b0 /
b1010 .
b100 -
b11 ,
b1 +
b10 *
b1010 %
b100 $
b11 #
$end
#0
$dumpvars
bx 6
bx 5
bx 4
03
b11 2
b0 1
b0 0
b0 )
b0 (
0'
0&
b0 "
0!
$end
#5000
1&
#10000
0&
#15000
1&
#20000
0&
b1010 5
b0 4
1'
#25000
b0 2
13
b1010 0
1&
#30000
0&
b0 6
#35000
b1010 "
b1010 1
b1001 0
1&
#40000
0&
b1 6
#45000
b1001 "
b1001 1
b1000 0
1&
#50000
0&
b10 6
#55000
b1000 "
b1000 1
b111 0
1&
#60000
0&
b11 6
#65000
b111 "
b111 1
b110 0
1&
#70000
0&
b100 6
#75000
b110 "
b110 1
b101 0
1&
#80000
0&
b101 6
#85000
b101 "
b101 1
b100 0
1&
#90000
0&
b110 6
#95000
b100 "
b100 1
b11 0
1&
#100000
0&
b111 6
#105000
b11 "
b11 1
b10 0
1&
#110000
0&
b1000 6
#115000
b10 "
b10 1
b1 0
1&
#120000
0&
b1001 6
#125000
b1 "
b1 1
b0 0
1&
#130000
0&
b1010 6
#135000
b0 "
b0 1
03
1!
1&
#140000
0&
b1011 6
#145000
1&
#150000
0&
b1100 6
#155000
1&
#160000
0&
b1 (
b1 )
b100 5
b1 4
b1101 6
#165000
b1 2
13
0!
b100 0
1&
#170000
0&
b0 6
#175000
b100 "
b100 1
b11 0
1&
#180000
0&
b1 6
#185000
b11 "
b11 1
b10 0
1&
#190000
0&
b10 6
#195000
b10 "
b10 1
b1 0
1&
#200000
0&
b11 6
#205000
b1 "
b1 1
b0 0
1&
#210000
0&
b100 6
#215000
b0 "
b0 1
03
1!
1&
#220000
0&
b101 6
#225000
1&
#230000
0&
b110 6
#235000
1&
#240000
0&
b10 (
b10 )
b11 5
b10 4
b111 6
#245000
b10 2
13
0!
b11 0
1&
#250000
0&
b0 6
#255000
b11 "
b11 1
b10 0
1&
#260000
0&
b1 6
#265000
b10 "
b10 1
b1 0
1&
#270000
0&
b10 6
#275000
b1 "
b1 1
b0 0
1&
#280000
0&
b11 6
#285000
b0 "
b0 1
03
1!
1&
#290000
0&
b100 6
#295000
1&
#300000
0&
b101 6
#305000
1&
#310000
0&
b110 6
